{
	"type" : "CASH_INCOME",
	"uuid" : "3f89bb0a-95c2-4ed3-8910-96cb3a25eba5",
	"number" : 9,
	"closeSum" : "247.5",
	"openDate" : "2016-09-13T14:52:36.000+0000",
	"closeDate" : "2016-09-13T14:52:36.000+0000",
	"deviceUuid" : "5a188de4-49b8-4cb4-800e-eb6b5202437e",
	"sessionUUID" : "150b9045-ce0f-4ee8-9222-291c6f94ea7b",
	"openUserCode" : null,
	"openUserUuid" : "123e4567-e89b-12d3-a456-426655440000",
	"transactions" : [{
			"id" : "37",
			"type" : "DOCUMENT_OPEN",
			"uuid" : null,
			"userCode" : null,
			"userUuid" : "123e4567-e89b-12d3-a456-426655440000",
			"clientName" : null,
			"clientPhone" : null,
			"couponNumber" : null,
			"creationDate" : "2016-09-13T14:52:36.000+0000",
			"baseDocumentUUID" : null,
			"baseDocumentNumber" : null
		}, {
			"id" : "38",
			"sum" : 247.5,
			"type" : "REGISTER_BILLS",
			"uuid" : null,
			"quantity" : 1,
			"userCode" : null,
			"userUuid" : "123e4567-e89b-12d3-a456-426655440000",
			"creationDate" : "2016-09-13T14:52:36.000+0000",
			"denomination" : 247.5
		}, {
			"id" : "39",
			"type" : "DOCUMENT_CLOSE_FPRINT",
			"uuid" : null,
			"total" : 247.5,
			"userCode" : null,
			"userUuid" : "123e4567-e89b-12d3-a456-426655440000",
			"creationDate" : "2016-09-13T14:52:36.000+0000",
			"receiptNumber" : "73",
			"sessionNumber" : "0",
			"documentNumber" : "121"
		}, {
			"id" : "40",
			"sum" : 247.5,
			"type" : "CASH_INCOME",
			"uuid" : null,
			"userCode" : null,
			"userUuid" : "123e4567-e89b-12d3-a456-426655440000",
			"creationDate" : "2016-09-13T14:52:36.000+0000"
		}
	],
	"closeUserCode" : null,
	"closeUserUuid" : "123e4567-e89b-12d3-a456-426655440000",
	"sessionNumber" : "1",
	"closeResultSum" : "247.5"
}
