{
	"type" : "FPRINT",//Тип документа (строка).
	"uuid" : "61be4c2a-08f9-4118-9133-2ce78a3f0a73",//Идентификатор документа (uuid4).
    "extras" : {},//Поля с дополнительной информацией. По токену приложения, с которым пришёл запрос, Эвотор определяет какие дополнительные поля необходимо вернуть. Может быть пустым объектом или принимать значение null.
	"number" : 13,//Номер документа (число).
	"closeSum" : "0",
	"openDate" : "2016-09-14T07:40:26.000+0000",//Дата открытия документа (строка, обязательное поле).
	"closeDate" : "2016-09-14T07:40:26.000+0000",//Дата закрытия документа (строка, обязательное поле).
	"deviceUuid" : "5a188de4-49b8-4cb4-800e-eb6b5202437e",//Идентификатор смарт-терминала (uuid4) (строка, обязательное поле).
	"sessionUUID" : "991d1329-2cf6-4adb-8d74-cfd88e2ea6f2",//Идентификатор смены (uuid4) (строка, обязательное поле).
	"openUserCode" : null,
	"openUserUuid" : "123e4567-e89b-12d3-a456-426655440000",//Идентификатор сотрудника (пользователя), который открыл документ(uuid4) (строка, обязательное поле).
	"transactions" : [{//Дата совершения транзакции.
			"id" : "37",//Числовой идентификатор транзакции (строка).
			"cash" : 0,
			"type" : "FPRINT_X_REPORT",//Тип транзакции (строка).
			"uuid" : null,//Идентификатор транзакции (uuid4). Этот идентификатор исползуют приложения.
			"total" : 0,
			"proceeds" : 7256.4,
			"userCode" : null,
			"userUuid" : "123e4567-e89b-12d3-a456-426655440000",//Идентификатор сотрудника (например, кассира), совершившего транзакцию (uuid4).
			"creationDate" : "2016-09-14T07:40:26.000+0000",//Дата совершения транзакции.
			"receiptNumber" : 80,
			"sessionNumber" : 0,//Номер смены.
			"documentNumber" : 138//Номер документа.
		}
	],
	"closeUserCode" : null,
	"closeUserUuid" : "123e4567-e89b-12d3-a456-426655440000",//Идентификатор сотрудника (пользователя), который открыл документ(uuid4).
	"sessionNumber" : "3",//Номер смены.
	"closeResultSum" : "7256.4"
}
